<Root>
	<!-- City Yields --> 
	<Entry>
		<zType>EFFECTCITY_BASE</zType>
		<Name>TEXT_EFFECTCITY_BASE</Name>
		<aiYieldRate>
			<Pair>
				<zIndex>YIELD_MONEY</zIndex>
				<iValue>20</iValue>
			</Pair>
			<Pair>
				<zIndex>YIELD_LOCAL_MATERIAL</zIndex>
				<iValue>20</iValue>
			</Pair>
			<Pair>
				<zIndex>YIELD_FUEL</zIndex>
				<iValue>20</iValue>
			</Pair>
			<Pair>
				<zIndex>YIELD_CIVICS</zIndex>
				<iValue>30</iValue>
			</Pair>
			<Pair>
				<zIndex>YIELD_MANPOWER</zIndex>
				<iValue>20</iValue>
			</Pair>
			<Pair>
				<zIndex>YIELD_GROWTH</zIndex>
				<iValue>-50</iValue>
			</Pair>
			<Pair>
				<zIndex>YIELD_TRAINING</zIndex>
				<iValue>0</iValue>
			</Pair>
		</aiYieldRate>
	</Entry>
	<Entry>
		<zType>EFFECTCITY_CAPITAL</zType>
		<Name>TEXT_EFFECTCITY_CAPITAL</Name>
		<bSingle>1</bSingle>
		<aiYieldRate>
			<Pair>
				<zIndex>YIELD_MONEY</zIndex>
				<iValue>30</iValue>
			</Pair>
			<Pair>
				<zIndex>YIELD_MANPOWER</zIndex>
				<iValue>30</iValue>
			</Pair>
			<Pair>
				<zIndex>YIELD_INTEL</zIndex>
				<iValue>10</iValue>
			</Pair>
			<Pair>
				<zIndex>YIELD_SCIENCE</zIndex>
				<iValue>30</iValue>
			</Pair>
			<Pair>
				<zIndex>YIELD_CULTURE</zIndex>
				<iValue>10</iValue>
			</Pair>
		</aiYieldRate>
	</Entry>
	<Entry>
		<zType>EFFECTCITY_CONNECTED</zType>
		<Name>TEXT_EFFECTCITY_CONNECTED</Name>
		<bSingle>1</bSingle>
		<aiYieldRate>
			<Pair>
				<zIndex>YIELD_GROWTH</zIndex>
				<iValue>10</iValue>
			</Pair>
			<Pair>
				<zIndex>YIELD_DISCONTENT</zIndex>
				<iValue>-10</iValue>
			</Pair>
		</aiYieldRate>
		<aiYieldModifier>
			<Pair>
				<zIndex>YIELD_MAINTENANCE</zIndex>
				<iValue>-5</iValue>
			</Pair>
		</aiYieldModifier>
	</Entry>
	<Entry>
		<zType>EFFECTCITY_DAMAGED</zType>
		<Name>TEXT_EFFECTCITY_DAMAGED</Name>
		<bSingle>1</bSingle>
		<aiYieldRate>
			<Pair>
				<zIndex>YIELD_GROWTH</zIndex>
				<iValue>-5</iValue>
			</Pair>
			<Pair>
				<zIndex>YIELD_LOCAL_MATERIAL</zIndex>
				<iValue>-10</iValue>
			</Pair>
		</aiYieldRate>
	</Entry>
	<Entry>
		<zType>EFFECTCITY_CITIZEN</zType>
		<Name>TEXT_EFFECTCITY_CITIZEN</Name>
		<aiYieldRate>
			<Pair>
				<zIndex>YIELD_ORDERS</zIndex>
				<iValue>5</iValue>
			</Pair>
			<Pair>
				<zIndex>YIELD_GROWTH</zIndex>
				<iValue>20</iValue>
			</Pair>
			<Pair>
				<zIndex>YIELD_LOCAL_MATERIAL</zIndex>
				<iValue>20</iValue>
			</Pair>
			<Pair>
				<zIndex>YIELD_MANPOWER</zIndex>
				<iValue>20</iValue>
			</Pair>
		</aiYieldRate>
		<aaiEffectCityYieldRate></aaiEffectCityYieldRate>
	</Entry>
	<Entry>
		<zType>EFFECTCITY_POPULATION</zType>
		<Name>TEXT_EFFECTCITY_POPULATION</Name>
		<aiYieldRate>
			<Pair>
				<zIndex>YIELD_MAINTENANCE</zIndex>
				<iValue>-20</iValue>
			</Pair>
			<Pair>
				<zIndex>YIELD_ORDERS</zIndex>
				<iValue>5</iValue>
			</Pair>
			<Pair>
				<zIndex>YIELD_GROWTH</zIndex>
				<iValue>-30</iValue>
			</Pair>
		</aiYieldRate>
	</Entry>
	<Entry>
		<zType>EFFECTCITY_CULTURE_WEAK</zType>
		<Name>TEXT_EFFECTCITY_CULTURE_WEAK</Name>
		<SourceCulture>CULTURE_WEAK</SourceCulture>
		<bSingle>1</bSingle>
		<aiYieldRatePopulation>
			<Pair>
				<zIndex>YIELD_GROWTH</zIndex>
				<iValue>-10</iValue>
			</Pair>
			<Pair>
				<zIndex>YIELD_LOCAL_MATERIAL</zIndex>
				<iValue>-10</iValue>
			</Pair>
			<Pair>
				<zIndex>YIELD_MAINTENANCE</zIndex>
				<iValue>-10</iValue>
			</Pair>
		</aiYieldRatePopulation>
	</Entry>
	<Entry>
		<zType>EFFECTCITY_CULTURE_DEVELOPING</zType>
		<Name>TEXT_EFFECTCITY_CULTURE_DEVELOPING</Name>
		<SourceCulture>CULTURE_DEVELOPING</SourceCulture>
		<bSingle>1</bSingle>
		<aiYieldRatePopulation>
			<Pair>
				<zIndex>YIELD_GROWTH</zIndex>
				<iValue>-20</iValue>
			</Pair>
			<Pair>
				<zIndex>YIELD_LOCAL_MATERIAL</zIndex>
				<iValue>-20</iValue>
			</Pair>
			<Pair>
				<zIndex>YIELD_MAINTENANCE</zIndex>
				<iValue>-20</iValue>
			</Pair>
		</aiYieldRatePopulation>
	</Entry>
	<Entry>
		<zType>EFFECTCITY_CULTURE_STRONG</zType>
		<Name>TEXT_EFFECTCITY_CULTURE_STRONG</Name>
		<SourceCulture>CULTURE_STRONG</SourceCulture>
		<bSingle>1</bSingle>
		<aiYieldRatePopulation>
			<Pair>
				<zIndex>YIELD_GROWTH</zIndex>
				<iValue>-30</iValue>
			</Pair>
			<Pair>
				<zIndex>YIELD_LOCAL_MATERIAL</zIndex>
				<iValue>-30</iValue>
			</Pair>
			<Pair>
				<zIndex>YIELD_MAINTENANCE</zIndex>
				<iValue>-30</iValue>
			</Pair>
		</aiYieldRatePopulation>
	</Entry>
	<Entry>
		<zType>EFFECTCITY_CULTURE_LEGENDARY</zType>
		<Name>TEXT_EFFECTCITY_CULTURE_LEGENDARY</Name>
		<SourceCulture>CULTURE_LEGENDARY</SourceCulture>
		<bSingle>1</bSingle>
		<aiYieldRatePopulation>
			<Pair>
				<zIndex>YIELD_GROWTH</zIndex>
				<iValue>-40</iValue>
			</Pair>
			<Pair>
				<zIndex>YIELD_LOCAL_MATERIAL</zIndex>
				<iValue>-40</iValue>
			</Pair>
			<Pair>
				<zIndex>YIELD_MAINTENANCE</zIndex>
				<iValue>-40</iValue>
			</Pair>
		</aiYieldRatePopulation>
	</Entry>
	<!-- Family Class --> 
	<Entry>
		<zType>EFFECTCITY_FAMILYCLASS_STATESMEN</zType>
		<aiYieldRate>
			<Pair>
				<zIndex>YIELD_CIVICS</zIndex>
				<iValue>10</iValue>
			</Pair>
		</aiYieldRate>
		<aiYieldRateOpinion>
		</aiYieldRateOpinion>
	</Entry>
	<Entry>
		<zType>EFFECTCITY_FAMILYCLASS_STATESMEN_SEAT</zType>
		<Name>TEXT_FAMILYCLASS_STATESMEN</Name>
		<Source>TEXT_EFFECTCITY_SEAT_SOURCE</Source>
		<EffectCityUnlock>EFFECTCITY_FAMILYCLASS_STATESMEN_SEAT_COURT</EffectCityUnlock>
		<SourceFamilyClass>FAMILYCLASS_STATESMEN</SourceFamilyClass>
		<bSingle>1</bSingle>
	</Entry>
	<!-- Projects --> 
	<Entry>
		<zType>EFFECTCITY_PROJECT_ARCHIVE_1</zType>
		<Name>TEXT_PROJECT_ARCHIVE_1</Name>
		<SourceProject>PROJECT_ARCHIVE_1</SourceProject>
		<bSingle>1</bSingle>
		<aiYieldRate>
			<Pair>
				<zIndex>YIELD_SCIENCE</zIndex>
				<iValue>10</iValue>
			</Pair>
		</aiYieldRate>
	</Entry>
	<Entry>
		<zType>EFFECTCITY_PROJECT_ARCHIVE_2</zType>
		<Name>TEXT_PROJECT_ARCHIVE_2</Name>
		<SourceProject>PROJECT_ARCHIVE_2</SourceProject>
		<bSingle>1</bSingle>
		<aiYieldRate>
			<Pair>
				<zIndex>YIELD_SCIENCE</zIndex>
				<iValue>20</iValue>
			</Pair>
		</aiYieldRate>
	</Entry>
	<Entry>
		<zType>EFFECTCITY_PROJECT_ARCHIVE_3</zType>
		<Name>TEXT_PROJECT_ARCHIVE_3</Name>
		<SourceProject>PROJECT_ARCHIVE_3</SourceProject>
		<bSingle>1</bSingle>
		<aiYieldRate>
			<Pair>
				<zIndex>YIELD_SCIENCE</zIndex>
				<iValue>30</iValue>
			</Pair>
		</aiYieldRate>
	</Entry>
	<Entry>
		<zType>EFFECTCITY_PROJECT_ARCHIVE_4</zType>
		<Name>TEXT_PROJECT_ARCHIVE_4</Name>
		<SourceProject>PROJECT_ARCHIVE_4</SourceProject>
		<bSingle>1</bSingle>
		<aiYieldRate>
			<Pair>
				<zIndex>YIELD_SCIENCE</zIndex>
				<iValue>40</iValue>
			</Pair>
		</aiYieldRate>
	</Entry>
	<Entry>
		<zType>EFFECTCITY_PROJECT_FORUM_1</zType>
		<Name>TEXT_PROJECT_FORUM_1</Name>
		<SourceProject>PROJECT_FORUM_1</SourceProject>
		<bSingle>1</bSingle>
		<aiYieldRate>
			<Pair>
				<zIndex>YIELD_CIVICS</zIndex>
				<iValue>20</iValue>
			</Pair>
		</aiYieldRate>
	</Entry>
	<Entry>
		<zType>EFFECTCITY_PROJECT_FORUM_2</zType>
		<Name>TEXT_PROJECT_FORUM_2</Name>
		<SourceProject>PROJECT_FORUM_2</SourceProject>
		<bSingle>1</bSingle>
		<aiYieldRate>
			<Pair>
				<zIndex>YIELD_CIVICS</zIndex>
				<iValue>20</iValue>
			</Pair>
		</aiYieldRate>
	</Entry>
	<Entry>
		<zType>EFFECTCITY_PROJECT_FORUM_3</zType>
		<Name>TEXT_PROJECT_FORUM_3</Name>
		<SourceProject>PROJECT_FORUM_3</SourceProject>
		<bSingle>1</bSingle>
		<aiYieldRate>
			<Pair>
				<zIndex>YIELD_CIVICS</zIndex>
				<iValue>50</iValue>
			</Pair>
		</aiYieldRate>
	</Entry>
	<Entry>
		<zType>EFFECTCITY_PROJECT_FORUM_4</zType>
		<Name>TEXT_PROJECT_FORUM_4</Name>
		<SourceProject>PROJECT_FORUM_4</SourceProject>
		<bSingle>1</bSingle>
		<aiYieldRate>
			<Pair>
				<zIndex>YIELD_CIVICS</zIndex>
				<iValue>60</iValue>
			</Pair>
		</aiYieldRate>
	</Entry>
	<Entry>
		<zType>EFFECTCITY_PROJECT_WALLS</zType>
		<Name>TEXT_PROJECT_WALLS</Name>
		<SourceProject>PROJECT_WALLS</SourceProject>
		<iCityHP>20</iCityHP>
		<bSingle>1</bSingle>
		<aiYieldRateDefending>
			<Pair>
				<zIndex>YIELD_DISCONTENT</zIndex>
				<iValue>-10</iValue>
			</Pair>
		</aiYieldRateDefending>
	</Entry>
	<Entry>
		<zType>EFFECTCITY_PROJECT_TOWERS</zType>
		<Name>TEXT_PROJECT_TOWERS</Name>
		<SourceProject>PROJECT_TOWERS</SourceProject>
		<iCityHP>20</iCityHP>
		<iRangeChange>0</iRangeChange>
		<iStrengthModifier>25</iStrengthModifier>
		<bSingle>1</bSingle>
		<aiYieldRateDefending>
			<Pair>
				<zIndex>YIELD_DISCONTENT</zIndex>
				<iValue>-10</iValue>
			</Pair>
		</aiYieldRateDefending>
	</Entry>
	<!-- Religion --> 
	<Entry>
		<zType>EFFECTCITY_THEOLOGY_GNOSTICISM</zType>
		<Name>TEXT_THEOLOGY_GNOSTICISM</Name>
		<SourceTheology>THEOLOGY_GNOSTICISM</SourceTheology>
		<aaiEffectCityYieldRate></aaiEffectCityYieldRate>
	</Entry>
	<Entry>
		<zType>EFFECTCITY_IMPROVEMENTCLASS_HOLY_SITE</zType>
		<Name>TEXT_IMPROVEMENTCLASS_HOLY_SITE</Name>
		<aiYieldModifier>
			<Pair>
				<zIndex>YIELD_DEVOTION</zIndex>
				<iValue>20</iValue>
			</Pair>
		</aiYieldModifier>
	</Entry>
	<!-- Difficulty --> 
	<Entry>
		<zType>EFFECTCITY_DIFFICULTY_ABLE</zType>
		<Name>TEXT_DIFFICULTY_ABLE</Name>
		<SourceDifficulty>DIFFICULTY_ABLE</SourceDifficulty>
		<bSingle>1</bSingle>
		<aiYieldRate>
			<Pair>
				<zIndex>YIELD_DISCONTENT</zIndex>
				<iValue>50</iValue>
			</Pair>
			<Pair>
				<zIndex>YIELD_MONEY</zIndex>
				<iValue>200</iValue>
			</Pair>
		</aiYieldRate>
	</Entry>
	<Entry>
		<zType>EFFECTCITY_DIFFICULTY_JUST</zType>
		<Name>TEXT_DIFFICULTY_JUST</Name>
		<SourceDifficulty>DIFFICULTY_JUST</SourceDifficulty>
		<bSingle>1</bSingle>
		<aiYieldRate>
			<Pair>
				<zIndex>YIELD_DISCONTENT</zIndex>
				<iValue>60</iValue>
			</Pair>
			<Pair>
				<zIndex>YIELD_MONEY</zIndex>
				<iValue>150</iValue>
			</Pair>
		</aiYieldRate>
	</Entry>
	<Entry>
		<zType>EFFECTCITY_DIFFICULTY_GOOD</zType>
		<Name>TEXT_DIFFICULTY_GOOD</Name>
		<SourceDifficulty>DIFFICULTY_GOOD</SourceDifficulty>
		<bSingle>1</bSingle>
		<aiYieldRate>
			<Pair>
				<zIndex>YIELD_DISCONTENT</zIndex>
				<iValue>80</iValue>
			</Pair>
			<Pair>
				<zIndex>YIELD_MONEY</zIndex>
				<iValue>50</iValue>
			</Pair>
		</aiYieldRate>
	</Entry>
	<Entry>
		<zType>EFFECTCITY_DIFFICULTY_STRONG</zType>
		<Name>TEXT_DIFFICULTY_STRONG</Name>
		<SourceDifficulty>DIFFICULTY_STRONG</SourceDifficulty>
		<bSingle>1</bSingle>
		<aiYieldRate>
			<Pair>
				<zIndex>YIELD_DISCONTENT</zIndex>
				<iValue>90</iValue>
			</Pair>
			<Pair>
				<zIndex>YIELD_MONEY</zIndex>
				<iValue>30</iValue>
			</Pair>
		</aiYieldRate>
	</Entry>
	<Entry>
		<zType>EFFECTCITY_DIFFICULTY_NOBLE</zType>
		<Name>TEXT_DIFFICULTY_NOBLE</Name>
		<SourceDifficulty>DIFFICULTY_NOBLE</SourceDifficulty>
		<bSingle>1</bSingle>
		<aiYieldRate>
			<Pair>
				<zIndex>YIELD_DISCONTENT</zIndex>
				<iValue>100</iValue>
			</Pair>
			<Pair>
				<zIndex>YIELD_MONEY</zIndex>
				<iValue>20</iValue>
			</Pair>
		</aiYieldRate>
	</Entry>
	<Entry>
		<zType>EFFECTCITY_DIFFICULTY_GLORIOUS</zType>
		<Name>TEXT_DIFFICULTY_GLORIOUS</Name>
		<SourceDifficulty>DIFFICULTY_GLORIOUS</SourceDifficulty>
		<bSingle>1</bSingle>
		<aiYieldRate>
			<Pair>
				<zIndex>YIELD_DISCONTENT</zIndex>
				<iValue>110</iValue>
			</Pair>
			<Pair>
				<zIndex>YIELD_MONEY</zIndex>
				<iValue>10</iValue>
			</Pair>
		</aiYieldRate>
	</Entry>
	<Entry>
		<zType>EFFECTCITY_DIFFICULTY_MAGNIFICENT</zType>
		<Name>TEXT_DIFFICULTY_MAGNIFICENT</Name>
		<SourceDifficulty>DIFFICULTY_MAGNIFICENT</SourceDifficulty>
		<bSingle>1</bSingle>
		<aiYieldRate>
			<Pair>
				<zIndex>YIELD_DISCONTENT</zIndex>
				<iValue>130</iValue>
			</Pair>
			<Pair>
				<zIndex>YIELD_MONEY</zIndex>
				<iValue>10</iValue>
			</Pair>
		</aiYieldRate>
	</Entry>
	<Entry>
		<zType>EFFECTCITY_DIFFICULTY_GREAT</zType>
		<Name>TEXT_DIFFICULTY_GREAT</Name>
		<SourceDifficulty>DIFFICULTY_GREAT</SourceDifficulty>
		<bSingle>1</bSingle>
		<aiYieldRate>
			<Pair>
				<zIndex>YIELD_DISCONTENT</zIndex>
				<iValue>150</iValue>
			</Pair>
			<Pair>
				<zIndex>YIELD_MONEY</zIndex>
				<iValue>10</iValue>
			</Pair>
		</aiYieldRate>
	</Entry>
</Root>
